{
  "id": "00000000-0000-0000-0000-000000000000",
  "prevId": "",
  "version": "7",
  "dialect": "postgresql",
  "tables": {
    "public.allocations": {
      "name": "allocations",
      "schema": "",
      "columns": {
        "count": {
          "name": "count",
          "type": "integer",
          "primaryKey": false,
          "notNull": false
        },
        "id": {
          "name": "id",
          "type": "uuid",
          "primaryKey": true,
          "notNull": true,
          "default": "uuid_generate_v4()"
        },
        "golfer_id": {
          "name": "golfer_id",
          "type": "uuid",
          "primaryKey": false,
          "notNull": false
        },
        "prize_id": {
          "name": "prize_id",
          "type": "uuid",
          "primaryKey": false,
          "notNull": false
        },
        "lock_indicator": {
          "name": "lock_indicator",
          "type": "boolean",
          "primaryKey": false,
          "notNull": false
        }
      },
      "indexes": {},
      "foreignKeys": {
        "constraint_1": {
          "name": "constraint_1",
          "tableFrom": "allocations",
          "tableTo": "golfers",
          "schemaTo": "public",
          "columnsFrom": [
            "golfer_id"
          ],
          "columnsTo": [
            "id"
          ],
          "onDelete": "cascade",
          "onUpdate": "cascade"
        },
        "prize_id_foreign_key": {
          "name": "prize_id_foreign_key",
          "tableFrom": "allocations",
          "tableTo": "prizes",
          "schemaTo": "public",
          "columnsFrom": [
            "prize_id"
          ],
          "columnsTo": [
            "id"
          ],
          "onDelete": "cascade",
          "onUpdate": "cascade"
        }
      },
      "compositePrimaryKeys": {},
      "uniqueConstraints": {
        "golfer_prize": {
          "columns": [
            "golfer_id",
            "prize_id"
          ],
          "nullsNotDistinct": false,
          "name": "golfer_prize"
        }
      },
      "checkConstraints": {},
      "policies": {},
      "isRLSEnabled": false
    },
    "public.users": {
      "name": "users",
      "schema": "",
      "columns": {
        "id": {
          "name": "id",
          "type": "uuid",
          "primaryKey": true,
          "notNull": true,
          "default": "uuid_generate_v4()"
        },
        "name": {
          "name": "name",
          "type": "varchar(255)",
          "primaryKey": false,
          "notNull": true
        },
        "email": {
          "name": "email",
          "type": "text",
          "primaryKey": false,
          "notNull": true
        },
        "password": {
          "name": "password",
          "type": "text",
          "primaryKey": false,
          "notNull": true
        }
      },
      "indexes": {},
      "foreignKeys": {},
      "compositePrimaryKeys": {},
      "uniqueConstraints": {
        "users_email_key": {
          "columns": [
            "email"
          ],
          "nullsNotDistinct": false,
          "name": "users_email_key"
        }
      },
      "checkConstraints": {},
      "policies": {},
      "isRLSEnabled": false
    },
    "public.customers": {
      "name": "customers",
      "schema": "",
      "columns": {
        "id": {
          "name": "id",
          "type": "uuid",
          "primaryKey": true,
          "notNull": true,
          "default": "uuid_generate_v4()"
        },
        "name": {
          "name": "name",
          "type": "varchar(255)",
          "primaryKey": false,
          "notNull": true
        },
        "email": {
          "name": "email",
          "type": "varchar(255)",
          "primaryKey": false,
          "notNull": true
        },
        "image_url": {
          "name": "image_url",
          "type": "varchar(255)",
          "primaryKey": false,
          "notNull": true
        }
      },
      "indexes": {},
      "foreignKeys": {},
      "compositePrimaryKeys": {},
      "uniqueConstraints": {},
      "checkConstraints": {},
      "policies": {},
      "isRLSEnabled": false
    },
    "public.raffles": {
      "name": "raffles",
      "schema": "",
      "columns": {
        "decription": {
          "name": "decription",
          "type": "text",
          "primaryKey": false,
          "notNull": false
        },
        "id": {
          "name": "id",
          "type": "uuid",
          "primaryKey": true,
          "notNull": true,
          "default": "uuid_generate_v4()"
        }
      },
      "indexes": {},
      "foreignKeys": {},
      "compositePrimaryKeys": {},
      "uniqueConstraints": {},
      "checkConstraints": {},
      "policies": {},
      "isRLSEnabled": false
    },
    "public.awards": {
      "name": "awards",
      "schema": "",
      "columns": {
        "id": {
          "name": "id",
          "type": "uuid",
          "primaryKey": true,
          "notNull": true,
          "default": "uuid_generate_v4()"
        },
        "golfer_id": {
          "name": "golfer_id",
          "type": "uuid",
          "primaryKey": false,
          "notNull": false
        },
        "amount": {
          "name": "amount",
          "type": "integer",
          "primaryKey": false,
          "notNull": false
        }
      },
      "indexes": {},
      "foreignKeys": {
        "c1": {
          "name": "c1",
          "tableFrom": "awards",
          "tableTo": "golfers",
          "schemaTo": "public",
          "columnsFrom": [
            "golfer_id"
          ],
          "columnsTo": [
            "id"
          ],
          "onDelete": "cascade",
          "onUpdate": "cascade"
        }
      },
      "compositePrimaryKeys": {},
      "uniqueConstraints": {
        "awards_golfer_id_key": {
          "columns": [
            "golfer_id"
          ],
          "nullsNotDistinct": false,
          "name": "awards_golfer_id_key"
        }
      },
      "checkConstraints": {},
      "policies": {},
      "isRLSEnabled": false
    },
    "public.revenue": {
      "name": "revenue",
      "schema": "",
      "columns": {
        "month": {
          "name": "month",
          "type": "varchar(4)",
          "primaryKey": false,
          "notNull": true
        },
        "revenue": {
          "name": "revenue",
          "type": "integer",
          "primaryKey": false,
          "notNull": true
        }
      },
      "indexes": {},
      "foreignKeys": {},
      "compositePrimaryKeys": {},
      "uniqueConstraints": {
        "revenue_month_key": {
          "columns": [
            "month"
          ],
          "nullsNotDistinct": false,
          "name": "revenue_month_key"
        }
      },
      "checkConstraints": {},
      "policies": {},
      "isRLSEnabled": false
    },
    "public.golfers": {
      "name": "golfers",
      "schema": "",
      "columns": {
        "name": {
          "name": "name",
          "type": "text",
          "primaryKey": false,
          "notNull": false
        },
        "email": {
          "name": "email",
          "type": "text",
          "primaryKey": false,
          "notNull": false
        },
        "id": {
          "name": "id",
          "type": "uuid",
          "primaryKey": true,
          "notNull": true,
          "default": "uuid_generate_v4()"
        },
        "username": {
          "name": "username",
          "type": "text",
          "primaryKey": false,
          "notNull": false
        },
        "role": {
          "name": "role",
          "type": "text",
          "primaryKey": false,
          "notNull": false
        }
      },
      "indexes": {},
      "foreignKeys": {},
      "compositePrimaryKeys": {},
      "uniqueConstraints": {},
      "checkConstraints": {},
      "policies": {},
      "isRLSEnabled": false
    },
    "public.prizes": {
      "name": "prizes",
      "schema": "",
      "columns": {
        "summary": {
          "name": "summary",
          "type": "text",
          "primaryKey": false,
          "notNull": false
        },
        "description": {
          "name": "description",
          "type": "text",
          "primaryKey": false,
          "notNull": false
        },
        "raffle_id": {
          "name": "raffle_id",
          "type": "text",
          "primaryKey": false,
          "notNull": true
        },
        "id": {
          "name": "id",
          "type": "uuid",
          "primaryKey": true,
          "notNull": true,
          "default": "uuid_generate_v4()"
        },
        "winner": {
          "name": "winner",
          "type": "uuid",
          "primaryKey": false,
          "notNull": false
        }
      },
      "indexes": {},
      "foreignKeys": {
        "constraint_1": {
          "name": "constraint_1",
          "tableFrom": "prizes",
          "tableTo": "golfers",
          "schemaTo": "public",
          "columnsFrom": [
            "winner"
          ],
          "columnsTo": [
            "id"
          ],
          "onDelete": "no action",
          "onUpdate": "no action"
        }
      },
      "compositePrimaryKeys": {},
      "uniqueConstraints": {},
      "checkConstraints": {},
      "policies": {},
      "isRLSEnabled": false
    },
    "public.invoices": {
      "name": "invoices",
      "schema": "",
      "columns": {
        "id": {
          "name": "id",
          "type": "uuid",
          "primaryKey": true,
          "notNull": true,
          "default": "uuid_generate_v4()"
        },
        "customer_id": {
          "name": "customer_id",
          "type": "uuid",
          "primaryKey": false,
          "notNull": true
        },
        "amount": {
          "name": "amount",
          "type": "integer",
          "primaryKey": false,
          "notNull": true
        },
        "status": {
          "name": "status",
          "type": "varchar(255)",
          "primaryKey": false,
          "notNull": true
        },
        "date": {
          "name": "date",
          "type": "date",
          "primaryKey": false,
          "notNull": true
        }
      },
      "indexes": {},
      "foreignKeys": {},
      "compositePrimaryKeys": {},
      "uniqueConstraints": {},
      "checkConstraints": {},
      "policies": {},
      "isRLSEnabled": false
    },
    "public.nicknames": {
      "name": "nicknames",
      "schema": "",
      "columns": {
        "id": {
          "name": "id",
          "type": "uuid",
          "primaryKey": true,
          "notNull": true,
          "default": "uuid_generate_v4()"
        },
        "golfer_id": {
          "name": "golfer_id",
          "type": "uuid",
          "primaryKey": false,
          "notNull": true
        },
        "nickname": {
          "name": "nickname",
          "type": "text",
          "primaryKey": false,
          "notNull": false
        },
        "default_ind": {
          "name": "default_ind",
          "type": "boolean",
          "primaryKey": false,
          "notNull": false
        }
      },
      "indexes": {},
      "foreignKeys": {
        "constraint_1": {
          "name": "constraint_1",
          "tableFrom": "nicknames",
          "tableTo": "golfers",
          "schemaTo": "public",
          "columnsFrom": [
            "golfer_id"
          ],
          "columnsTo": [
            "id"
          ],
          "onDelete": "no action",
          "onUpdate": "no action"
        }
      },
      "compositePrimaryKeys": {},
      "uniqueConstraints": {},
      "checkConstraints": {},
      "policies": {},
      "isRLSEnabled": false
    }
  },
  "enums": {},
  "schemas": {},
  "sequences": {},
  "roles": {},
  "policies": {},
  "views": {
    "public.vw_nicknames": {
      "name": "vw_nicknames",
      "schema": "public",
      "columns": {
        "golfer_id": {
          "name": "golfer_id",
          "type": "uuid",
          "primaryKey": false,
          "notNull": false
        },
        "nickname": {
          "name": "nickname",
          "type": "text",
          "primaryKey": false,
          "notNull": false
        }
      },
      "isExisting": false,
      "definition": "SELECT golfer_id, nickname FROM nicknames WHERE default_ind = true",
      "materialized": false
    }
  },
  "_meta": {
    "schemas": {},
    "tables": {},
    "columns": {}
  },
  "internal": {
    "tables": {}
  }
}